CHANGES.txt
CONTRIBUTORS.txt
MANIFEST.in
README.txt
setup.cfg
setup.py
collective/.DS_Store
collective/__init__.py
collective.wowcharacter.egg-info/PKG-INFO
collective.wowcharacter.egg-info/SOURCES.txt
collective.wowcharacter.egg-info/dependency_links.txt
collective.wowcharacter.egg-info/entry_points.txt
collective.wowcharacter.egg-info/namespace_packages.txt
collective.wowcharacter.egg-info/not-zip-safe
collective.wowcharacter.egg-info/paster_plugins.txt
collective.wowcharacter.egg-info/requires.txt
collective.wowcharacter.egg-info/top_level.txt
collective/wowcharacter/.DS_Store
collective/wowcharacter/README.txt
collective/wowcharacter/__init__.py
collective/wowcharacter/config.py
collective/wowcharacter/configure.zcml
collective/wowcharacter/browser/.DS_Store
collective/wowcharacter/browser/__init__.py
collective/wowcharacter/browser/activity_api.py
collective/wowcharacter/browser/armory_api.py
collective/wowcharacter/browser/configure.zcml
collective/wowcharacter/browser/wowcharacter.py
collective/wowcharacter/browser/images/alliance.jpg
collective/wowcharacter/browser/images/down.png
collective/wowcharacter/browser/images/down2.png
collective/wowcharacter/browser/images/horde.jpg
collective/wowcharacter/browser/images/rss.png
collective/wowcharacter/browser/images/up.png
collective/wowcharacter/browser/images/up2.png
collective/wowcharacter/browser/stylesheets/wowcharacter.css
collective/wowcharacter/browser/templates/wowcharacter.pt
collective/wowcharacter/content/__init__.py
collective/wowcharacter/content/configure.zcml
collective/wowcharacter/content/wowcharacter.py
collective/wowcharacter/interfaces/__init__.py
collective/wowcharacter/interfaces/wowcharacter.py
collective/wowcharacter/locales/collective.wowcharacter.pot
collective/wowcharacter/locales/de/LC_MESSAGES/collective.wowcharacter.mo
collective/wowcharacter/locales/de/LC_MESSAGES/collective.wowcharacter.po
collective/wowcharacter/portlets/.DS_Store
collective/wowcharacter/portlets/README.txt
collective/wowcharacter/portlets/__init__.py
collective/wowcharacter/portlets/configure.zcml
collective/wowcharacter/portlets/realmstatus_api.py
collective/wowcharacter/portlets/version.txt
collective/wowcharacter/portlets/wowrealmstatus.pt
collective/wowcharacter/portlets/wowrealmstatus.py
collective/wowcharacter/portlets/profiles/default/metadata.xml
collective/wowcharacter/portlets/profiles/default/portlets.xml
