Metadata-Version: 1.0
Name: collective.wowcharacter
Version: 0.5
Summary: An installable content type for WoW characters
Home-page: http://code.google.com/p/collectivewowcharacter/
Author: Marc Goetz
Author-email: goetz.marc@googlemail.com
License: GPL
Keywords: content type wow warcraft character
Platform: UNKNOWN
Classifier: Framework :: Plone
Classifier: Intended Audience :: Developers
Classifier: Topic :: Software Development :: Libraries :: Python Modules
Classifier: License :: OSI Approved :: GNU General Public License (GPL)
